phenocam_snow/__init__.py
phenocam_snow/data.py
phenocam_snow/get_all_images.py
phenocam_snow/model.py
phenocam_snow/predict.py
phenocam_snow/train.py
phenocam_snow/utils.py
phenocam_snow-0.1.1.dist-info/LICENSE
phenocam_snow-0.1.1.dist-info/METADATA
phenocam_snow-0.1.1.dist-info/WHEEL
phenocam_snow-0.1.1.dist-info/top_level.txt
phenocam_snow-0.1.1.dist-info/RECORD
